MCPStack/__init__.py
MCPStack/__main__.py
MCPStack/cli.py
MCPStack/core/__init__.py
MCPStack/core/config.py
MCPStack/core/mcp_config_generator/__init__.py
MCPStack/core/mcp_config_generator/mcp_config_generators/__init__.py
MCPStack/core/mcp_config_generator/mcp_config_generators/claude_mcp_config.py
MCPStack/core/mcp_config_generator/mcp_config_generators/fast_mcp_config.py
MCPStack/core/mcp_config_generator/mcp_config_generators/universal_mcp_config.py
MCPStack/core/mcp_config_generator/registry.py
MCPStack/core/preset/__init__.py
MCPStack/core/preset/base.py
MCPStack/core/preset/presets/__init__.py
MCPStack/core/preset/presets/example_preset.py
MCPStack/core/preset/registry.py
MCPStack/core/server.py
MCPStack/core/tool/__init__.py
MCPStack/core/tool/base.py
MCPStack/core/tool/cli/__init__.py
MCPStack/core/tool/cli/base.py
MCPStack/core/utils/__init__.py
MCPStack/core/utils/exceptions.py
MCPStack/core/utils/logging.py
MCPStack/stack.py
MCPStack/tools/__init__.py
MCPStack/tools/hello_world/__init__.py
MCPStack/tools/hello_world/cli.py
MCPStack/tools/hello_world/hello_world.py
MCPStack/tools/registry.py
mcpstack-0.0.2.dist-info/METADATA
mcpstack-0.0.2.dist-info/WHEEL
mcpstack-0.0.2.dist-info/entry_points.txt
mcpstack-0.0.2.dist-info/licenses/LICENSE
mcpstack-0.0.2.dist-info/RECORD
