Metadata-Version: 2.4
Name: mcpstack
Version: 0.0.2
Summary: MCPStack: a generic, composable stack for building and running MCP tool pipelines.
Keywords: mcp,model-context-protocol,pipelines,llm,tooling,cli,scikit-learn-pipelines
Author-Email: Provost Simon <sgp29@kent.ac.uk>
License-Expression: MIT
Classifier: Development Status :: 4 - Beta
Classifier: Intended Audience :: Developers
Classifier: Intended Audience :: Science/Research
Classifier: Topic :: Software Development :: Libraries
Classifier: Topic :: Software Development :: Build Tools
Classifier: Programming Language :: Python :: 3
Classifier: Programming Language :: Python :: 3.10
Classifier: Programming Language :: Python :: 3.11
Classifier: Programming Language :: Python :: 3.12
Classifier: Operating System :: OS Independent
Project-URL: Homepage, https://github.com/MCP-Pipeline/
Project-URL: Repository, https://github.com/MCP-Pipeline/MCPStack
Project-URL: Documentation, https://github.com/MCP-Pipeline/MCPStack
Project-URL: Issues, https://github.com/MCP-Pipeline/MCPStack/issues
Project-URL: Changelog, https://github.com/MCP-Pipeline/MCPStack/releases
Requires-Python: >=3.10
Requires-Dist: typer>=0.9.0
Requires-Dist: rich>=13.0.0
Requires-Dist: fastmcp>=0.1.0
Requires-Dist: beartype>=0.21.0
Requires-Dist: thefuzz>=0.22.1
Requires-Dist: rich-pyfiglet>=0.1.4
Requires-Dist: click==8.1.8
Requires-Dist: pytest-cov>=6.2.1
Requires-Dist: pytest==7.4.3
Requires-Dist: pytest-asyncio>=0.23.8
Provides-Extra: devtools
Requires-Dist: appdirs>=1.4.0; extra == "devtools"
Requires-Dist: pyaml>=25.7.0; extra == "devtools"
